prettystack/__init__.py
prettystack/console.jinja2
prettystack/exceptions.py
prettystack/prettystack_template.py
prettystack/traceback.py
prettystack/utils.py
prettystack-0.4.0.dist-info/LICENSE.txt
prettystack-0.4.0.dist-info/METADATA
prettystack-0.4.0.dist-info/WHEEL
prettystack-0.4.0.dist-info/top_level.txt
prettystack-0.4.0.dist-info/RECORD
